.gitignore
.readthedocs.yml
LICENCE
README.md
requirements.txt
requirements_all.txt
setup.py
version.py
.binder/requirements.txt
.github/workflows/release.yml
.github/workflows/tf.yml
AI4Water.egg-info/PKG-INFO
AI4Water.egg-info/SOURCES.txt
AI4Water.egg-info/dependency_links.txt
AI4Water.egg-info/requires.txt
AI4Water.egg-info/top_level.txt
ai4water/__init__.py
ai4water/_main.py
ai4water/_optimize.py
ai4water/backend.py
ai4water/functional.py
ai4water/keract_mod.py
ai4water/main.py
ai4water/nn_tools.py
ai4water/pytorch_models.py
ai4water/tf_attributes.py
ai4water/tf_models.py
ai4water/datasets/__init__.py
ai4water/datasets/_arcade.py
ai4water/datasets/_datasets.py
ai4water/datasets/_grimedb.py
ai4water/datasets/_grqa.py
ai4water/datasets/_hyperspectral.py
ai4water/datasets/_npctr.py
ai4water/datasets/_quadica.py
ai4water/datasets/_rc4uscoast.py
ai4water/datasets/_swatch.py
ai4water/datasets/arg_busan.csv
ai4water/datasets/camels.py
ai4water/datasets/download_pangaea.py
ai4water/datasets/download_zenodo.py
ai4water/datasets/mtropics.py
ai4water/datasets/utils.py
ai4water/datasets/water_quality/__init__.py
ai4water/datasets/water_quality/_busan_beach.py
ai4water/datasets/water_quality/_doce_river.py
ai4water/datasets/water_quality/_river_chem_siberia.py
ai4water/datasets/water_quality/_selune_river.py
ai4water/eda/__init__.py
ai4water/eda/_main.py
ai4water/eda/utils.py
ai4water/envs/__init__.py
ai4water/et/__init__.py
ai4water/et/converter.py
ai4water/et/et_methods.py
ai4water/et/global_variables.py
ai4water/et/utils.py
ai4water/experiments/__init__.py
ai4water/experiments/_cls.py
ai4water/experiments/_dl.py
ai4water/experiments/_main.py
ai4water/experiments/_rgr.py
ai4water/experiments/utils.py
ai4water/hyperopt/__init__.py
ai4water/hyperopt/_fanova.py
ai4water/hyperopt/_main.py
ai4water/hyperopt/_optuna_fanova.py
ai4water/hyperopt/_space.py
ai4water/hyperopt/utils.py
ai4water/models/__init__.py
ai4water/models/utils.py
ai4water/models/_tensorflow/__init__.py
ai4water/models/_tensorflow/_functions.py
ai4water/models/_tensorflow/_models.py
ai4water/models/_tensorflow/attention_layers.py
