Metadata-Version: 2.1
Name: AI4Water
Version: 1.6
Summary: Platform for developing data driven based models for sequential/tabular data
Home-page: https://github.com/AtrCheema/AI4Water
Author: Ather Abbas
Author-email: ather_abbas786@yahoo.com
License: UNKNOWN
Platform: UNKNOWN
Classifier: Development Status :: 4 - Beta
Classifier: Natural Language :: English
Classifier: Intended Audience :: Science/Research
Classifier: Intended Audience :: Developers
Classifier: Operating System :: Microsoft :: Windows
Classifier: Operating System :: POSIX :: Linux
Classifier: Programming Language :: Python :: 3
Classifier: Programming Language :: Python :: 3.5
Classifier: Programming Language :: Python :: 3.6
Classifier: Programming Language :: Python :: 3.7
Classifier: Programming Language :: Python :: 3.8
Classifier: Programming Language :: Python :: 3.8
Classifier: Programming Language :: Python :: 3.9
Provides-Extra: all
Provides-Extra: hpo
Provides-Extra: post_process
Provides-Extra: exp
Provides-Extra: eda
Provides-Extra: tf
Provides-Extra: tf2
Provides-Extra: torch
Provides-Extra: tf_hpo
Provides-Extra: torch_hpo_requires
Provides-Extra: ml
Provides-Extra: ml_hpo
License-File: LICENCE
